mplplots/__init__.py
mplplots/plots.py
nnodely/__init__.py
nnodely/nnodely.py
nnodely/basic/__init__.py
nnodely/basic/loss.py
nnodely/basic/model.py
nnodely/basic/modeldef.py
nnodely/basic/optimizer.py
nnodely/basic/relation.py
nnodely/exporter/__init__.py
nnodely/exporter/emptyexporter.py
nnodely/exporter/export.py
nnodely/exporter/reporter.py
nnodely/exporter/standardexporter.py
nnodely/layers/__init__.py
nnodely/layers/activation.py
nnodely/layers/arithmetic.py
nnodely/layers/equationlearner.py
nnodely/layers/fir.py
nnodely/layers/fuzzify.py
nnodely/layers/input.py
nnodely/layers/interpolation.py
nnodely/layers/linear.py
nnodely/layers/localmodel.py
nnodely/layers/output.py
nnodely/layers/parameter.py
nnodely/layers/parametricfunction.py
nnodely/layers/part.py
nnodely/layers/timeoperation.py
nnodely/layers/trigonometric.py
nnodely/operators/__init__.py
nnodely/operators/composer.py
nnodely/operators/exporter.py
nnodely/operators/loader.py
nnodely/operators/network.py
nnodely/operators/trainer.py
nnodely/operators/validator.py
nnodely/support/__init__.py
nnodely/support/earlystopping.py
nnodely/support/fixstepsolver.py
nnodely/support/initializer.py
nnodely/support/jsonutils.py
nnodely/support/logger.py
nnodely/support/mathutils.py
nnodely/support/utils.py
nnodely/visualizer/__init__.py
nnodely/visualizer/emptyvisualizer.py
nnodely/visualizer/mplnotebookvisualizer.py
nnodely/visualizer/mplvisualizer.py
nnodely/visualizer/textvisualizer.py
nnodely/visualizer/dynamicmpl/functionplot.py
nnodely/visualizer/dynamicmpl/fuzzyplot.py
nnodely/visualizer/dynamicmpl/resultsplot.py
nnodely/visualizer/dynamicmpl/trainingplot.py
nnodely-1.5.1.dist-info/licenses/LICENSE
nnodely-1.5.1.dist-info/METADATA
nnodely-1.5.1.dist-info/WHEEL
nnodely-1.5.1.dist-info/top_level.txt
nnodely-1.5.1.dist-info/RECORD
