Metadata-Version: 2.4
Name: nnodely
Version: 1.5.1
Summary: Model-structured neural network framework for the modeling and control of physical systems
Author-email: Gastone Pietro Rosati Papini <tonegas@gmail.com>
License: MIT License
Project-URL: Homepage, https://github.com/tonegas/nnodely
Classifier: Programming Language :: Python :: 3
Classifier: License :: OSI Approved :: MIT License
Classifier: Operating System :: OS Independent
Requires-Python: <3.13,>=3.10
License-File: LICENSE
Requires-Dist: numpy==1.26.4; platform_machine == "x86_64" and python_version == "3.10"
Requires-Dist: torch==2.2.2; platform_machine == "x86_64" and python_version == "3.10"
Requires-Dist: torch==2.6.0; platform_machine != "x86_64" or python_version != "3.10"
Requires-Dist: numpy
Requires-Dist: onnx
Requires-Dist: pandas
Requires-Dist: reportlab
Requires-Dist: matplotlib
Requires-Dist: onnxruntime
Requires-Dist: graphviz
Dynamic: license-file
